chaos_ml/__init__.py
chaos_ml/cli.py
chaos_ml/datasets.py
chaos_ml/export.py
chaos_ml/factory.py
chaos_ml/metrics.py
chaos_ml/models.py
chaos_ml/plots.py
chaos_ml/systems.py
chaos_ml/training.py
chaos_ml/tuner.py
chaos_ml/version.py
chaos_ml-0.1.3.dist-info/METADATA
chaos_ml-0.1.3.dist-info/WHEEL
chaos_ml-0.1.3.dist-info/top_level.txt
chaos_ml-0.1.3.dist-info/RECORD
