Metadata-Version: 2.4
Name: chaos-ml
Version: 0.1.3
Summary: Unified chaotic systems forecasting toolkit
Author: Nacim
License: MIT
Requires-Python: >=3.11
Requires-Dist: numpy
Requires-Dist: scipy
Requires-Dist: scikit-learn
Requires-Dist: matplotlib
Requires-Dist: torch
Requires-Dist: streamlit
Requires-Dist: optuna
Requires-Dist: altair
